pysolplanet/__init__.py
pysolplanet/__main__.py
pysolplanet-0.0.1.dist-info/LICENSE
pysolplanet-0.0.1.dist-info/METADATA
pysolplanet-0.0.1.dist-info/WHEEL
pysolplanet-0.0.1.dist-info/top_level.txt
pysolplanet-0.0.1.dist-info/RECORD
