Metadata-Version: 2.1
Name: pysolplanet
Version: 0.0.1
Summary: Python package for interacting with Solplanet PV inverters through the Wi-Fi Stick
Author-email: Fufs <42976807+Fufs@users.noreply.github.com>
Project-URL: Homepage, https://github.com/Fufs/pysolplanet
Project-URL: Bug Tracker, https://github.com/Fufs/pysolplanet/issues
Classifier: Programming Language :: Python :: 3
Classifier: License :: OSI Approved :: MIT License
Classifier: Operating System :: OS Independent
Requires-Python: >=3.7
License-File: LICENSE
Requires-Dist: aiohttp (==3.1.8)
